{
  "isInitial": true,
  "files": [
    {
      "index": 1,
      "name": "VFS/1CDDBF1F/1CDDBF1F.blc",
      "hash": "1430268200448271d9a3079bf8b68aba",
      "size": 220,
      "type": 4,
      "md5": "1430268200448271d9a3079bf8b68aba",
      "urlPath": null,
      "manifest": 7
    },
    {
      "index": 2,
      "name": "VFS/1CDDBF1F/66C13C288255A5955AEB453DC02844F8.chk",
      "hash": null,
      "size": 36623409,
      "type": 4,
      "md5": "995e7a8ffcd5c9099fb553170a50e20b",
      "urlPath": null,
      "manifest": 0
    },
    {
      "index": 3,
      "name": "VFS/DAFE52C9/DAFE52C9.blc",
      "hash": "4e04de4a739fd05d5c4371ac3d551cba",
      "size": 235,
      "type": 5,
      "md5": "4e04de4a739fd05d5c4371ac3d551cba",
      "urlPath": null,
      "manifest": 7
    },
    {
      "index": 4,
      "name": "VFS/DAFE52C9/7A394421445F4B63CF0EAE7DA60DC893.chk",
      "hash": null,
      "size": 46111,
      "type": 5,
      "md5": "8ffe98928d5aabf06d2228cc586c2ba1",
      "urlPath": null,
      "manifest": 0
    },
    {
      "index": 5,
      "name": "VFS/07A1BB91/07A1BB91.blc",
      "hash": "62dcc5af31ce82c4e3be9aa085f1f5be",
      "size": 379,
      "type": 1,
      "md5": "62dcc5af31ce82c4e3be9aa085f1f5be",
      "urlPath": null,
      "manifest": 7
    },
    {
      "index": 6,
      "name": "VFS/07A1BB91/0E3664B88A6ABD1A27A2951237D5C5E0.chk",
      "hash": null,
      "size": 577924,
      "type": 1,
      "md5": "60d9e995e007e8aa9f6b58965d4c59cc",
      "urlPath": null,
      "manifest": 0
    },
    {
      "index": 7,
      "name": "VFS/07A1BB91/83C163475E272203AF9CA1B25D59AD51.chk",
      "hash": null,
      "size": 11905122,
      "type": 1,
      "md5": "dfdd08adf46470141f4172d3bc8adb54",
      "urlPath": null,
      "manifest": 0
    },
    {
      "index": 8,
      "name": "VFS/0CE8FA57/0CE8FA57.blc",
      "hash": "d8efaf993abbfd1e9ecd750818168f59",
      "size": 111132,
      "type": 2,
      "md5": "d8efaf993abbfd1e9ecd750818168f59",
      "urlPath": null,
      "manifest": 3
    },
    {
      "index": 9,
      "name": "VFS/0CE8FA57/CA858660957B4A898DF6AA7F556C35BD.chk",
      "hash": null,
      "size": 434509664,
      "type": 2,
      "md5": "d9141c56fed4dd5e21146ea2c4e9e3f3",
      "urlPath": null,
      "manifest": 4
    },
    {
      "index": 10,
      "name": "VFS/3C9D9D2D/3C9D9D2D.blc",
      "hash": "7c8ccc3f8ed599b4d87d86c9d98e9854",
      "size": 237,
      "type": 3,
      "md5": "7c8ccc3f8ed599b4d87d86c9d98e9854",
      "urlPath": null,
      "manifest": 7
    },
    {
      "index": 11,
      "name": "VFS/3C9D9D2D/BC171009668C61D60FC0C7C7DE35446A.chk",
      "hash": null,
      "size": 285042,
      "type": 3,
      "md5": "ef5d28a6f46390b1a05cbd65d1326425",
      "urlPath": null,
      "manifest": 0
    }
  ],
  "types": null,
  "version": null,
  "rebootVersion": ""
}
